riseup_vpn_configurator/__init__.py
riseup_vpn_configurator/riseup-vpn.yaml
riseup_vpn_configurator-1.3.0.dist-info/LICENSE
riseup_vpn_configurator-1.3.0.dist-info/METADATA
riseup_vpn_configurator-1.3.0.dist-info/WHEEL
riseup_vpn_configurator-1.3.0.dist-info/entry_points.txt
riseup_vpn_configurator-1.3.0.dist-info/RECORD
