Metadata-Version: 2.1
Name: riseup-vpn-configurator
Version: 1.3.0
Summary: a simple command line tool to get RiseupVPN up and running
Home-page: https://github.com/kmille/riseup-vpn-configurator
License: GPL-3.0-only
Author: kmille
Author-email: github@androidloves.me
Requires-Python: >=3.10,<4.0
Classifier: License :: OSI Approved :: GNU General Public License v3 (GPLv3)
Classifier: Programming Language :: Python :: 3
Classifier: Programming Language :: Python :: 3.10
Classifier: Programming Language :: Python :: 3.11
Classifier: Programming Language :: Python :: 3.12
Requires-Dist: icmplib (>=3.0.4,<4.0.0)
Requires-Dist: jinja2 (>=3.1.2,<4.0.0)
Requires-Dist: psutil (>=6.0.0,<7.0.0)
Requires-Dist: pyasn1 (>=0.4.8,<0.5.0)
Requires-Dist: pyasn1-modules (>=0.2.8,<0.3.0)
Requires-Dist: pyyaml (>=6.0,<7.0)
Requires-Dist: requests (>=2.28.2,<3.0.0)
Project-URL: Repository, https://github.com/kmille/riseup-vpn-configurator
